Metadata-Version: 1.0
Name: flask-urls
Version: 0.9.2
Summary: A collection of URL-related functions for Flask applications.
Home-page: http://sjl.bitbucket.org/flask-urls/
Author: Steve Losh
Author-email: steve@stevelosh.com
License: MIT
Platform: any
Classifier: Development Status :: 4 - Beta
Classifier: Environment :: Web Environment
Classifier: Intended Audience :: Developers
Classifier: License :: OSI Approved :: MIT License
Classifier: Operating System :: OS Independent
Classifier: Programming Language :: Python
Classifier: Topic :: Internet :: WWW/HTTP :: Dynamic Content
Classifier: Topic :: Software Development :: Libraries :: Python Modules
